dtanys/__init__.py
dtanys/__version__.py
dtanys/dtanys.py
dtanys/future.py
dtanys-1.0.6.dist-info/LICENSE
dtanys-1.0.6.dist-info/METADATA
dtanys-1.0.6.dist-info/WHEEL
dtanys-1.0.6.dist-info/top_level.txt
dtanys-1.0.6.dist-info/RECORD
